mirmap/__init__.py
mirmap/evolution.py
mirmap/if_exe_phast.py
mirmap/if_lib_spatt.py
mirmap/if_lib_viennarna.py
mirmap/interval.py
mirmap/model.py
mirmap/prob.py
mirmap/prob_binomial.py
mirmap/prob_exact.py
mirmap/scores.py
mirmap/target.py
mirmap/targetscan.py
mirmap/targetscan_model.py
mirmap/thermo.py
mirmap/utils.py
mirmap_scripts/__init__.py
mirmap_scripts/mirmap.py
miRmap-2.0.0.dist-info/LICENSE
miRmap-2.0.0.dist-info/METADATA
miRmap-2.0.0.dist-info/WHEEL
miRmap-2.0.0.dist-info/entry_points.txt
miRmap-2.0.0.dist-info/top_level.txt
miRmap-2.0.0.dist-info/RECORD
