Metadata-Version: 2.1
Name: miRmap
Version: 2.0.0
Summary: Comprehensive prediction of microRNA target repression strength
Author: Charles E. Vejnar
License: GNU General Public License v3 (GPLv3)
Project-URL: homepage, https://git.sr.ht/~vejnar/miRmap
Classifier: License :: OSI Approved :: GNU General Public License v3 (GPLv3)
Classifier: Programming Language :: Python :: 3
Classifier: Topic :: Scientific/Engineering :: Bio-Informatics
Requires-Python: >=3.11
License-File: LICENSE
Requires-Dist: dendropy
Requires-Dist: ViennaRNA
